odoo/addons/partner_contact_personal_information_page/README.rst
odoo/addons/partner_contact_personal_information_page/__init__.py
odoo/addons/partner_contact_personal_information_page/__manifest__.py
odoo/addons/partner_contact_personal_information_page/i18n/da.po
odoo/addons/partner_contact_personal_information_page/i18n/de.po
odoo/addons/partner_contact_personal_information_page/i18n/es.po
odoo/addons/partner_contact_personal_information_page/i18n/fi.po
odoo/addons/partner_contact_personal_information_page/i18n/fr.po
odoo/addons/partner_contact_personal_information_page/i18n/hr_HR.po
odoo/addons/partner_contact_personal_information_page/i18n/hu.po
odoo/addons/partner_contact_personal_information_page/i18n/it.po
odoo/addons/partner_contact_personal_information_page/i18n/nl.po
odoo/addons/partner_contact_personal_information_page/i18n/partner_contact_personal_information_page.pot
odoo/addons/partner_contact_personal_information_page/i18n/pt.po
odoo/addons/partner_contact_personal_information_page/i18n/pt_BR.po
odoo/addons/partner_contact_personal_information_page/i18n/pt_PT.po
odoo/addons/partner_contact_personal_information_page/i18n/sl.po
odoo/addons/partner_contact_personal_information_page/readme/CONTRIBUTORS.rst
odoo/addons/partner_contact_personal_information_page/readme/DESCRIPTION.rst
odoo/addons/partner_contact_personal_information_page/readme/USAGE.rst
odoo/addons/partner_contact_personal_information_page/static/description/icon.png
odoo/addons/partner_contact_personal_information_page/static/description/index.html
odoo/addons/partner_contact_personal_information_page/views/res_partner.xml
odoo14_addon_partner_contact_personal_information_page-14.0.1.0.1.dev7.dist-info/METADATA
odoo14_addon_partner_contact_personal_information_page-14.0.1.0.1.dev7.dist-info/WHEEL
odoo14_addon_partner_contact_personal_information_page-14.0.1.0.1.dev7.dist-info/top_level.txt
odoo14_addon_partner_contact_personal_information_page-14.0.1.0.1.dev7.dist-info/RECORD
