Metadata-Version: 2.1
Name: odoo14-addon-partner-contact-personal-information-page
Version: 14.0.1.0.1.dev7
Summary: Add a page to contacts form to put personal information
Home-page: https://github.com/OCA/partner-contact
Author: Nicolas JEUDY,Odoo Community Association (OCA)
Author-email: support@odoo-community.org
License: AGPL-3
Platform: UNKNOWN
Classifier: Programming Language :: Python
Classifier: Framework :: Odoo
Classifier: Framework :: Odoo :: 14.0
Classifier: License :: OSI Approved :: GNU Affero General Public License v3
Requires-Python: >=3.6
Requires-Dist: odoo <14.1dev,>=14.0a
